Workbook

Sheet Итоги
A1: «Первый чек»: эффект для банка, затраты и срок окупаемости
A2: Модель на 36 месяцев: месяцы 1–3 — подготовка и интеграция, 4–6 — пилот на группе клиентов, с 7-го — тиражирование. Суммы — млн ₽. Все допущения — на листе «Допущения», источники — на листе «Источники».
A4: Показатель | B4: Пессимистичный | C4: Базовый | D4: Оптимистичный
A5: Активных пользователей помощника на 36-й месяц | B5: =Расчёт!AL6 -> 172800 | C5: =Расчёт!AL29 -> 345600 | D5: =Расчёт!AL52 -> 518400
A6: Новых ИП за счёт помощника за 3 года | B6: =SUM(Расчёт!C7:AL7) -> 889.25146 | C6: =SUM(Расчёт!C30:AL30) -> 5928.3431 | D6: =SUM(Расчёт!C53:AL53) -> 16006.526
A7: Эффект, год 1 | B7: =SUM(Расчёт!C12:N12)/10^6 -> 0.43220971 | C7: =SUM(Расчёт!C35:N35)/10^6 -> 3.5515755 | D7: =SUM(Расчёт!C58:N58)/10^6 -> 11.449325
A8: Эффект, год 2 | B8: =SUM(Расчёт!O12:Z12)/10^6 -> 4.8977804 | C8: =SUM(Расчёт!O35:Z35)/10^6 -> 45.898234 | D8: =SUM(Расчёт!O58:Z58)/10^6 -> 160.03511
A9: Эффект, год 3 | B9: =SUM(Расчёт!AA12:AL12)/10^6 -> 10.874283 | C9: =SUM(Расчёт!AA35:AL35)/10^6 -> 109.49276 | D9: =SUM(Расчёт!AA58:AL58)/10^6 -> 395.98224
A10: Затраты, год 1 | B10: =SUM(Расчёт!C20:N20)/10^6 -> 34.6 | C10: =SUM(Расчёт!C43:N43)/10^6 -> 34.6 | D10: =SUM(Расчёт!C66:N66)/10^6 -> 38.65
A11: Затраты, год 2 | B11: =SUM(Расчёт!O20:Z20)/10^6 -> 19.9 | C11: =SUM(Расчёт!O43:Z43)/10^6 -> 24.45 | D11: =SUM(Расчёт!O66:Z66)/10^6 -> 24.95
A12: Затраты, год 3 | B12: =SUM(Расчёт!AA20:AL20)/10^6 -> 24.4 | C12: =SUM(Расчёт!AA43:AL43)/10^6 -> 25 | D12: =SUM(Расчёт!AA66:AL66)/10^6 -> 25.6
A13: Накопленный денежный поток за 3 года | B13: =Расчёт!AL22/10^6 -> -62.695727 | C13: =Расчёт!AL45/10^6 -> 74.892574 | D13: =Расчёт!AL68/10^6 -> 478.26667
A14: Срок окупаемости, месяцев | B14: =IF(COUNT(Расчёт!C23:AL23)=0,"не окупается за 36 мес.",MIN(Расчёт!C23:AL23)) -> не окупается за 36 мес. | C14: =IF(COUNT(Расчёт!C46:AL46)=0,"не окупается за 36 мес.",MIN(Расчёт!C46:AL46)) -> 26 | D14: =IF(COUNT(Расчёт!C69:AL69)=0,"не окупается за 36 мес.",MIN(Расчёт!C69:AL69)) -> 18
A15: ROI за 3 года | B15: =IFERROR(SUM(Расчёт!C12:AL12)/SUM(Расчёт!C20:AL20)-1,0) -> -0.79462265 | C15: =IFERROR(SUM(Расчёт!C35:AL35)/SUM(Расчёт!C43:AL43)-1,0) -> 0.89104788 | D15: =IFERROR(SUM(Расчёт!C58:AL58)/SUM(Расчёт!C66:AL66)-1,0) -> 5.361734
A16: Структура эффекта за год 3: доход от ИП | B16: =IFERROR(SUM(Расчёт!AA9:AL9)/SUM(Расчёт!AA12:AL12),0) -> 0.78922874 | C16: =IFERROR(SUM(Расчёт!AA32:AL32)/SUM(Расчёт!AA35:AL35),0) -> 0.87091462 | D16: =IFERROR(SUM(Расчёт!AA55:AL55)/SUM(Расчёт!AA58:AL58),0) -> 0.91028439
A17: Структура эффекта за год 3: экономия поддержки | B17: =IFERROR(SUM(Расчёт!AA10:AL10)/SUM(Расчёт!AA12:AL12),0) -> 0.21077126 | C17: =IFERROR(SUM(Расчёт!AA33:AL33)/SUM(Расчёт!AA35:AL35),0) -> 0.041865528 | D17: =IFERROR(SUM(Расчёт!AA56:AL56)/SUM(Расчёт!AA58:AL58),0) -> 0.017364311
A18: Структура эффекта за год 3: удержание клиентов | B18: =IFERROR(SUM(Расчёт!AA11:AL11)/SUM(Расчёт!AA12:AL12),0) -> 0 | C18: =IFERROR(SUM(Расчёт!AA34:AL34)/SUM(Расчёт!AA35:AL35),0) -> 0.08721985 | D18: =IFERROR(SUM(Расчёт!AA57:AL57)/SUM(Расчёт!AA58:AL58),0) -> 0.072351295
A19: Затраты на одного активного пользователя в год 3, ₽ | B19: =IFERROR(SUM(Расчёт!AA20:AL20)/AVERAGE(Расчёт!AA6:AL6),0) -> 153.29935 | C19: =IFERROR(SUM(Расчёт!AA43:AL43)/AVERAGE(Расчёт!AA29:AL29),0) -> 78.534504 | D19: =IFERROR(SUM(Расчёт!AA66:AL66)/AVERAGE(Расчёт!AA52:AL52),0) -> 53.612888
A21: Как читать: эффект — дополнительный доход банка от ИП, открытых благодаря помощнику (только прирост), экономия поддержки и удержание самозанятых клиентов. Не учтены: остатки на картах самозанятых, доход от автоплатежа и чеков через банк (у банка эти сервисы уже есть), снижение штрафов клиентов. Пессимистичный сценарий за 3 года не окупается — это показывает, какие показатели пилота критичны: доля активных и конверсия в ИП.

Sheet Допущения
A1: Финансовая модель «Первый чек» для банка — допущения
A2: Синий шрифт — вводимые значения, жёлтая заливка — ключевые рычаги сценариев. Все значения, кроме базы клиентов и роста рынка, — допущения команды; их заменяют данными банка и проверяют на пилоте.
A4: Параметр | B4: Пессимистичный | C4: Базовый | D4: Оптимистичный | E4: Единица | F4: Источник или обоснование
A5: Клиенты и запуск
A6: Самозанятых клиентов банка на старте | B6: =$C$6 -> 1000000 | C6: 1000000 | D6: =$C$6 -> 1000000 | E6: чел. | F6: ВТБ: «число клиентов-самозанятых выросло на 43% и превысило 1 млн человек» по итогам 2025 года — Д. Бортников, «Газета.Ru», 18.02.2026 (см. «Источники», 1)
A7: Рост базы самозанятых клиентов в год | B7: =$C$7 -> 0.2 | C7: 0.2 | D7: =$C$7 -> 0.2 | E7: % в год | F7: Рост рынка: 17,3 млн самозанятых в августе 2026, +2,9 млн за год (≈ +20%) — ФНС, ТАСС 21.08.2026 (Источники, 2). У ВТБ в 2025 году рост был выше (+43%) — берём рыночный, консервативно
A8: Пилотная группа | B8: =$C$8 -> 20000 | C8: 20000 | D8: =$C$8 -> 20000 | E8: клиентов | F8: Допущение: группа клиентов с согласием на анализ поступлений
A9: Месяц начала пилота | B9: =$C$9 -> 4 | C9: 4 | D9: =$C$9 -> 4 | E9: мес. | F9: План: месяцы 1–3 — интервью, интеграция с операциями и сервисом банка
A10: Месяц начала тиражирования | B10: =$C$10 -> 7 | C10: 7 | D10: =$C$10 -> 7 | E10: мес. | F10: План: месяцы 4–6 — пилот, с 7-го — на всю базу
A11: Месяцев до выхода на целевую долю активных | B11: =$C$11 -> 12 | C11: 12 | D11: =$C$11 -> 12 | E11: мес. | F11: Допущение: линейный рост доли активных
A12: Сценарные рычаги
A13: Доля клиентов, пользующихся помощником хотя бы раз в месяц (MAU) | B13: 0.1 | C13: 0.2 | D13: 0.3 | E13: % клиентов | F13: Допущение; измеряется на пилоте. Помощник встроен в приложение и сам пишет при поступлениях, поэтому активность выше, чем у раздела справки
A14: Из активных за год открывают ИП с расчётным счётом в банке | B14: 0.01 | C14: 0.02 | D14: 0.03 | E14: % в год | F14: Допущение; измеряется на пилоте. Основа — клиенты у лимита 2,4 млн ₽ и с растущим доходом
A15: Инкрементальность: доля этих ИП, которых без помощника банк бы не получил | B15: 0.3 | C15: 0.5 | D15: 0.6 | E15: % | F15: Допущение: часть клиентов открыла бы ИП в банке и без помощника — учитываем только прирост
A16: Доход банка с одного ИП в год (РКО, эквайринг, остатки) | B16: 15000 | C16: 25000 | D16: 35000 | E16: ₽ в год | F16: Допущение; банк заменяет своими данными по микробизнесу
A17: Снижение оттока активных самозанятых клиентов | B17: 0 | C17: 0.01 | D17: 0.02 | E17: п.п. в год | F17: Допущение: доход за работу продолжает приходить на карту банка; в пессимистичном сценарии не учитывается
A18: Прочие эффекты
A19: Отток ИП в год | B19: =$C$19 -> 0.2 | C19: 0.2 | D19: =$C$19 -> 0.2 | E19: % в год | F19: Допущение: часть ИП закрывается или уходит в другой банк
A20: Обращений в поддержку по теме самозанятости на 1000 активных в месяц | B20: =$C$20 -> 20 | C20: 20 | D20: =$C$20 -> 20 | E20: обращений | F20: Допущение; банк заменяет данными поддержки
A21: Доля таких обращений, которые закрывает помощник | B21: =$C$21 -> 0.4 | C21: 0.4 | D21: =$C$21 -> 0.4 | E21: % | F21: Допущение; на эталоне помощник отвечает со ссылкой на 21 из 25 новых вопросов по закону (eval/results/holdout.md)
A22: Стоимость одного обращения в поддержку | B22: =$C$22 -> 150 | C22: 150 | D22: =$C$22 -> 150 | E22: ₽ | F22: Допущение
A23: Доход банка с клиента-самозанятого в год (карта, остатки, комиссии) | B23: =$C$23 -> 3000 | C23: 3000 | D23: =$C$23 -> 3000 | E23: ₽ в год | F23: Допущение; банк заменяет своими данными
A24: Затраты
A25: Полная стоимость сотрудника в месяц | B25: =$C$25 -> 400000 | C25: 400000 | D25: =$C$25 -> 400000 | E25: ₽ в месяц | F25: Допущение: зарплата, налоги, рабочее место
A26: Команда разработки и интеграции до тиражирования | B26: =$C$26 -> 6 | C26: 6 | D26: =$C$26 -> 6 | E26: FTE | F26: Допущение: 2 разработчика, ML-инженер, аналитик, тестировщик, менеджер
A27: Команда сопровождения и развития после тиражирования | B27: =$C$27 -> 3 | C27: 3 | D27: =$C$27 -> 3 | E27: FTE | F27: Допущение
A28: Юрист: проверка базы знаний и ответов специалистам | B28: =$C$28 -> 0.5 | C28: 0.5 | D28: =$C$28 -> 0.5 | E28: FTE | F28: Допущение: разъяснения ФНС опубликованы в разные годы, их нужно проверять
A29: Стоимость юриста в месяц | B29: =$C$29 -> 300000 | C29: 300000 | D29: =$C$29 -> 300000 | E29: ₽ в месяц | F29: Допущение
A30: Информационная безопасность: аудит, пентест, сопровождение | B30: =$C$30 -> 1500000 | C30: 1500000 | D30: =$C$30 -> 1500000 | E30: ₽ в год | F30: Допущение; 152-ФЗ, требования ИБ банка
A31: Продвижение внутри приложения банка | B31: =$C$31 -> 1000000 | C31: 1000000 | D31: =$C$31 -> 1000000 | E31: ₽ в год | F31: Допущение: баннеры и сценарии в приложении
A32: GPU-сервер в контуре банка | B32: =$C$32 -> 4000000 | C32: 4000000 | D32: =$C$32 -> 4000000 | E32: ₽ | F32: Допущение. Прототип отвечает за ~1 с на одной видеокарте RTX 5070 (eval/results/latest.md); для банка — серверные видеокарты
A33: Эксплуатация серверов: ЦОД, электроэнергия, поддержка | B33: =$C$33 -> 0.15 | C33: 0.15 | D33: =$C$33 -> 0.15 | E33: % стоимости в год | F33: Допущение
A34: Активных пользователей на один сервер | B34: =$C$34 -> 150000 | C34: 150000 | D34: =$C$34 -> 150000 | E34: чел. | F34: Допущение с запасом: ~6 вопросов на пользователя в месяц; уведомления о поступлениях считает программа без языковой модели
A35: Минимум серверов (с резервом) | B35: =$C$35 -> 2 | C35: 2 | D35: =$C$35 -> 2 | E35: шт. | F35: Один основной и один резервный

Sheet Расчёт
A1: Расчёт по месяцам, ₽ (36 месяцев, три сценария)
A3: Сценарий: Пессимистичный
A4: Месяц | C4: 1 | D4: 2 | E4: 3 | F4: 4 | G4: 5 | H4: 6 | I4: 7 | J4: 8 | K4: 9 | L4: 10 | M4: 11 | N4: 12 | O4: 13 | P4: 14 | Q4: 15 | R4: 16 | S4: 17 | T4: 18 | U4: 19 | V4: 20 | W4: 21 | X4: 22 | Y4: 23 | Z4: 24 | AA4: 25 | AB4: 26 | AC4: 27 | AD4: 28 | AE4: 29 | AF4: 30 | AG4: 31 | AH4: 32 | AI4: 33 | AJ4: 34 | AK4: 35 | AL4: 36
A5: База самозанятых клиентов | C5: =Допущения!$C$6*(1+Допущения!$C$7)^(C$4/12) -> 1015309.5 | D5: =Допущения!$C$6*(1+Допущения!$C$7)^(D$4/12) -> 1030853.3 | E5: =Допущения!$C$6*(1+Допущения!$C$7)^(E$4/12) -> 1046635.1 | F5: =Допущения!$C$6*(1+Допущения!$C$7)^(F$4/12) -> 1062658.6 | G5: =Допущения!$C$6*(1+Допущения!$C$7)^(G$4/12) -> 1078927.3 | H5: =Допущения!$C$6*(1+Допущения!$C$7)^(H$4/12) -> 1095445.1 | I5: =Допущения!$C$6*(1+Допущения!$C$7)^(I$4/12) -> 1112215.8 | J5: =Допущения!$C$6*(1+Допущения!$C$7)^(J$4/12) -> 1129243.2 | ... AL5: =Допущения!$C$6*(1+Допущения!$C$7)^(AL$4/12) -> 1728000
A6: Активных пользователей помощника | C6: =IF(C$4<Допущения!$C$9,0,IF(C$4<Допущения!$C$10,Допущения!$C$8*Допущения!$B$13,C5*Допущения!$B$13*MIN(1,(C$4-Допущения!$C$10+1)/Допущения!$C$11))) -> 0 | D6: =IF(D$4<Допущения!$C$9,0,IF(D$4<Допущения!$C$10,Допущения!$C$8*Допущения!$B$13,D5*Допущения!$B$13*MIN(1,(D$4-Допущения!$C$10+1)/Допущения!$C$11))) -> 0 | E6: =IF(E$4<Допущения!$C$9,0,IF(E$4<Допущения!$C$10,Допущения!$C$8*Допущения!$B$13,E5*Допущения!$B$13*MIN(1,(E$4-Допущения!$C$10+1)/Допущения!$C$11))) -> 0 | F6: =IF(F$4<Допущения!$C$9,0,IF(F$4<Допущения!$C$10,Допущения!$C$8*Допущения!$B$13,F5*Допущения!$B$13*MIN(1,(F$4-Допущения!$C$10+1)/Допущения!$C$11))) -> 2000 | G6: =IF(G$4<Допущения!$C$9,0,IF(G$4<Допущения!$C$10,Допущения!$C$8*Допущения!$B$13,G5*Допущения!$B$13*MIN(1,(G$4-Допущения!$C$10+1)/Допущения!$C$11))) -> 2000 | H6: =IF(H$4<Допущения!$C$9,0,IF(H$4<Допущения!$C$10,Допущения!$C$8*Допущения!$B$13,H5*Допущения!$B$13*MIN(1,(H$4-Допущения!$C$10+1)/Допущения!$C$11))) -> 2000 | I6: =IF(I$4<Допущения!$C$9,0,IF(I$4<Допущения!$C$10,Допущения!$C$8*Допущения!$B$13,I5*Допущения!$B$13*MIN(1,(I$4-Допущения!$C$10+1)/Допущения!$C$11))) -> 9268.465 | J6: =IF(J$4<Допущения!$C$9,0,IF(J$4<Допущения!$C$10,Допущения!$C$8*Допущения!$B$13,J5*Допущения!$B$13*MIN(1,(J$4-Допущения!$C$10+1)/Допущения!$C$11))) -> 18820.721 | ... AL6: =IF(AL$4<Допущения!$C$9,0,IF(AL$4<Допущения!$C$10,Допущения!$C$8*Допущения!$B$13,AL5*Допущения!$B$13*MIN(1,(AL$4-Допущения!$C$10+1)/Допущения!$C$11))) -> 172800
A7: Новых ИП (прирост за счёт помощника) | C7: =C6*Допущения!$B$14/12*Допущения!$B$15 -> 0 | D7: =D6*Допущения!$B$14/12*Допущения!$B$15 -> 0 | E7: =E6*Допущения!$B$14/12*Допущения!$B$15 -> 0 | F7: =F6*Допущения!$B$14/12*Допущения!$B$15 -> 0.5 | G7: =G6*Допущения!$B$14/12*Допущения!$B$15 -> 0.5 | H7: =H6*Допущения!$B$14/12*Допущения!$B$15 -> 0.5 | I7: =I6*Допущения!$B$14/12*Допущения!$B$15 -> 2.3171162 | J7: =J6*Допущения!$B$14/12*Допущения!$B$15 -> 4.7051801 | ... AL7: =AL6*Допущения!$B$14/12*Допущения!$B$15 -> 43.2
A8: ИП на обслуживании | C8: =0*(1-Допущения!$C$19/12)+C7 -> 0 | D8: =C8*(1-Допущения!$C$19/12)+D7 -> 0 | E8: =D8*(1-Допущения!$C$19/12)+E7 -> 0 | F8: =E8*(1-Допущения!$C$19/12)+F7 -> 0.5 | G8: =F8*(1-Допущения!$C$19/12)+G7 -> 0.99166667 | H8: =G8*(1-Допущения!$C$19/12)+H7 -> 1.4751389 | I8: =H8*(1-Допущения!$C$19/12)+I7 -> 3.7676695 | J8: =I8*(1-Допущения!$C$19/12)+J7 -> 8.4100551 | K8: =J8*(1-Допущения!$C$19/12)+K7 -> 15.435708 | ... AL8: =AK8*(1-Допущения!$C$19/12)+AL7 -> 742.48127
A9: Доход от ИП | C9: =C8*Допущения!$B$16/12 -> 0 | D9: =D8*Допущения!$B$16/12 -> 0 | E9: =E8*Допущения!$B$16/12 -> 0 | F9: =F8*Допущения!$B$16/12 -> 625 | G9: =G8*Допущения!$B$16/12 -> 1239.5833 | H9: =H8*Допущения!$B$16/12 -> 1843.9236 | I9: =I8*Допущения!$B$16/12 -> 4709.5869 | J9: =J8*Допущения!$B$16/12 -> 10512.569 | ... AL9: =AL8*Допущения!$B$16/12 -> 928101.59
A10: Экономия поддержки | C10: =C6*Допущения!$C$20/1000*Допущения!$C$21*Допущения!$C$22 -> 0 | D10: =D6*Допущения!$C$20/1000*Допущения!$C$21*Допущения!$C$22 -> 0 | E10: =E6*Допущения!$C$20/1000*Допущения!$C$21*Допущения!$C$22 -> 0 | F10: =F6*Допущения!$C$20/1000*Допущения!$C$21*Допущения!$C$22 -> 2400 | G10: =G6*Допущения!$C$20/1000*Допущения!$C$21*Допущения!$C$22 -> 2400 | H10: =H6*Допущения!$C$20/1000*Допущения!$C$21*Допущения!$C$22 -> 2400 | I10: =I6*Допущения!$C$20/1000*Допущения!$C$21*Допущения!$C$22 -> 11122.158 | J10: =J6*Допущения!$C$20/1000*Допущения!$C$21*Допущения!$C$22 -> 22584.865 | ... AL10: =AL6*Допущения!$C$20/1000*Допущения!$C$21*Допущения!$C$22 -> 207360
A11: Удержание клиентов | C11: =C6*Допущения!$B$17*Допущения!$C$23/12 -> 0 | D11: =D6*Допущения!$B$17*Допущения!$C$23/12 -> 0 | E11: =E6*Допущения!$B$17*Допущения!$C$23/12 -> 0 | F11: =F6*Допущения!$B$17*Допущения!$C$23/12 -> 0 | G11: =G6*Допущения!$B$17*Допущения!$C$23/12 -> 0 | H11: =H6*Допущения!$B$17*Допущения!$C$23/12 -> 0 | I11: =I6*Допущения!$B$17*Допущения!$C$23/12 -> 0 | J11: =J6*Допущения!$B$17*Допущения!$C$23/12 -> 0 | ... AL11: =AL6*Допущения!$B$17*Допущения!$C$23/12 -> 0
A12: Эффект всего | C12: =SUM(C9:C11) -> 0 | D12: =SUM(D9:D11) -> 0 | E12: =SUM(E9:E11) -> 0 | F12: =SUM(F9:F11) -> 3025 | G12: =SUM(G9:G11) -> 3639.5833 | H12: =SUM(H9:H11) -> 4243.9236 | I12: =SUM(I9:I11) -> 15831.745 | J12: =SUM(J9:J11) -> 33097.434 | ... AL12: =SUM(AL9:AL11) -> 1135461.6
A13: Серверов | C13: =MAX(Допущения!$C$35,ROUNDUP(C6/Допущения!$C$34,0)+1) -> 2 | D13: =MAX(Допущения!$C$35,ROUNDUP(D6/Допущения!$C$34,0)+1) -> 2 | E13: =MAX(Допущения!$C$35,ROUNDUP(E6/Допущения!$C$34,0)+1) -> 2 | F13: =MAX(Допущения!$C$35,ROUNDUP(F6/Допущения!$C$34,0)+1) -> 2 | G13: =MAX(Допущения!$C$35,ROUNDUP(G6/Допущения!$C$34,0)+1) -> 2 | H13: =MAX(Допущения!$C$35,ROUNDUP(H6/Допущения!$C$34,0)+1) -> 2 | I13: =MAX(Допущения!$C$35,ROUNDUP(I6/Допущения!$C$34,0)+1) -> 2 | J13: =MAX(Допущения!$C$35,ROUNDUP(J6/Допущения!$C$34,0)+1) -> 2 | ... AL13: =MAX(Допущения!$C$35,ROUNDUP(AL6/Допущения!$C$34,0)+1) -> 3
A14: Закупка серверов | C14: =(C13-0)*Допущения!$C$32 -> 8000000 | D14: =(D13-C13)*Допущения!$C$32 -> 0 | E14: =(E13-D13)*Допущения!$C$32 -> 0 | F14: =(F13-E13)*Допущения!$C$32 -> 0 | G14: =(G13-F13)*Допущения!$C$32 -> 0 | H14: =(H13-G13)*Допущения!$C$32 -> 0 | I14: =(I13-H13)*Допущения!$C$32 -> 0 | J14: =(J13-I13)*Допущения!$C$32 -> 0 | K14: =(K13-J13)*Допущения!$C$32 -> 0 | ... AL14: =(AL13-AK13)*Допущения!$C$32 -> 0
A15: Команда | C15: =IF(C$4<Допущения!$C$10,Допущения!$C$26,Допущения!$C$27)*Допущения!$C$25 -> 2400000 | D15: =IF(D$4<Допущения!$C$10,Допущения!$C$26,Допущения!$C$27)*Допущения!$C$25 -> 2400000 | E15: =IF(E$4<Допущения!$C$10,Допущения!$C$26,Допущения!$C$27)*Допущения!$C$25 -> 2400000 | F15: =IF(F$4<Допущения!$C$10,Допущения!$C$26,Допущения!$C$27)*Допущения!$C$25 -> 2400000 | G15: =IF(G$4<Допущения!$C$10,Допущения!$C$26,Допущения!$C$27)*Допущения!$C$25 -> 2400000 | H15: =IF(H$4<Допущения!$C$10,Допущения!$C$26,Допущения!$C$27)*Допущения!$C$25 -> 2400000 | I15: =IF(I$4<Допущения!$C$10,Допущения!$C$26,Допущения!$C$27)*Допущения!$C$25 -> 1200000 | J15: =IF(J$4<Допущения!$C$10,Допущения!$C$26,Допущения!$C$27)*Допущения!$C$25 -> 1200000 | ... AL15: =IF(AL$4<Допущения!$C$10,Допущения!$C$26,Допущения!$C$27)*Допущения!$C$25 -> 1200000
A16: Юрист | C16: =Допущения!$C$28*Допущения!$C$29 -> 150000 | D16: =Допущения!$C$28*Допущения!$C$29 -> 150000 | E16: =Допущения!$C$28*Допущения!$C$29 -> 150000 | F16: =Допущения!$C$28*Допущения!$C$29 -> 150000 | G16: =Допущения!$C$28*Допущения!$C$29 -> 150000 | H16: =Допущения!$C$28*Допущения!$C$29 -> 150000 | I16: =Допущения!$C$28*Допущения!$C$29 -> 150000 | J16: =Допущения!$C$28*Допущения!$C$29 -> 150000 | ... AL16: =Допущения!$C$28*Допущения!$C$29 -> 150000
A17: Информационная безопасность | C17: =Допущения!$C$30/12 -> 125000 | D17: =Допущения!$C$30/12 -> 125000 | E17: =Допущения!$C$30/12 -> 125000 | F17: =Допущения!$C$30/12 -> 125000 | G17: =Допущения!$C$30/12 -> 125000 | H17: =Допущения!$C$30/12 -> 125000 | I17: =Допущения!$C$30/12 -> 125000 | J17: =Допущения!$C$30/12 -> 125000 | ... AL17: =Допущения!$C$30/12 -> 125000
A18: Продвижение | C18: =IF(C$4>=Допущения!$C$10,Допущения!$C$31/12,0) -> 0 | D18: =IF(D$4>=Допущения!$C$10,Допущения!$C$31/12,0) -> 0 | E18: =IF(E$4>=Допущения!$C$10,Допущения!$C$31/12,0) -> 0 | F18: =IF(F$4>=Допущения!$C$10,Допущения!$C$31/12,0) -> 0 | G18: =IF(G$4>=Допущения!$C$10,Допущения!$C$31/12,0) -> 0 | H18: =IF(H$4>=Допущения!$C$10,Допущения!$C$31/12,0) -> 0 | I18: =IF(I$4>=Допущения!$C$10,Допущения!$C$31/12,0) -> 83333.333 | J18: =IF(J$4>=Допущения!$C$10,Допущения!$C$31/12,0) -> 83333.333 | ... AL18: =IF(AL$4>=Допущения!$C$10,Допущения!$C$31/12,0) -> 83333.333
A19: Эксплуатация серверов | C19: =C13*Допущения!$C$32*Допущения!$C$33/12 -> 100000 | D19: =D13*Допущения!$C$32*Допущения!$C$33/12 -> 100000 | E19: =E13*Допущения!$C$32*Допущения!$C$33/12 -> 100000 | F19: =F13*Допущения!$C$32*Допущения!$C$33/12 -> 100000 | G19: =G13*Допущения!$C$32*Допущения!$C$33/12 -> 100000 | H19: =H13*Допущения!$C$32*Допущения!$C$33/12 -> 100000 | I19: =I13*Допущения!$C$32*Допущения!$C$33/12 -> 100000 | J19: =J13*Допущения!$C$32*Допущения!$C$33/12 -> 100000 | ... AL19: =AL13*Допущения!$C$32*Допущения!$C$33/12 -> 150000
A20: Затраты всего | C20: =SUM(C14:C19) -> 10775000 | D20: =SUM(D14:D19) -> 2775000 | E20: =SUM(E14:E19) -> 2775000 | F20: =SUM(F14:F19) -> 2775000 | G20: =SUM(G14:G19) -> 2775000 | H20: =SUM(H14:H19) -> 2775000 | I20: =SUM(I14:I19) -> 1658333.3 | J20: =SUM(J14:J19) -> 1658333.3 | ... AL20: =SUM(AL14:AL19) -> 1708333.3
A21: Денежный поток | C21: =C12-C20 -> -10775000 | D21: =D12-D20 -> -2775000 | E21: =E12-E20 -> -2775000 | F21: =F12-F20 -> -2771975 | G21: =G12-G20 -> -2771360.4 | H21: =H12-H20 -> -2770756.1 | I21: =I12-I20 -> -1642501.6 | J21: =J12-J20 -> -1625235.9 | ... AL21: =AL12-AL20 -> -572871.75
A22: Накопленный денежный поток | C22: =0+C21 -> -10775000 | D22: =C22+D21 -> -13550000 | E22: =D22+E21 -> -16325000 | F22: =E22+F21 -> -19096975 | G22: =F22+G21 -> -21868335 | H22: =G22+H21 -> -24639091 | I22: =H22+I21 -> -26281593 | J22: =I22+J21 -> -27906829 | K22: =J22+K21 -> -29511472 | ... AL22: =AK22+AL21 -> -62695727
A23: Месяц окупаемости (отметка) | C23: =IF(C22>=0,C$4,"") | D23: =IF(AND(D22>=0,C22<0),D$4,"") | E23: =IF(AND(E22>=0,D22<0),E$4,"") | F23: =IF(AND(F22>=0,E22<0),F$4,"") | G23: =IF(AND(G22>=0,F22<0),G$4,"") | H23: =IF(AND(H22>=0,G22<0),H$4,"") | I23: =IF(AND(I22>=0,H22<0),I$4,"") | J23: =IF(AND(J22>=0,I22<0),J$4,"") | K23: =IF(AND(K22>=0,J22<0),K$4,"") | ... AL23: =IF(AND(AL22>=0,AK22<0),AL$4,"")
A26: Сценарий: Базовый
A27: Месяц | C27: 1 | D27: 2 | E27: 3 | F27: 4 | G27: 5 | H27: 6 | I27: 7 | J27: 8 | K27: 9 | L27: 10 | M27: 11 | N27: 12 | O27: 13 | P27: 14 | Q27: 15 | R27: 16 | S27: 17 | T27: 18 | U27: 19 | V27: 20 | W27: 21 | X27: 22 | Y27: 23 | Z27: 24 | AA27: 25 | AB27: 26 | AC27: 27 | AD27: 28 | AE27: 29 | AF27: 30 | AG27: 31 | AH27: 32 | AI27: 33 | AJ27: 34 | AK27: 35 | AL27: 36
A28: База самозанятых клиентов | C28: =Допущения!$C$6*(1+Допущения!$C$7)^(C$27/12) -> 1015309.5 | D28: =Допущения!$C$6*(1+Допущения!$C$7)^(D$27/12) -> 1030853.3 | E28: =Допущения!$C$6*(1+Допущения!$C$7)^(E$27/12) -> 1046635.1 | F28: =Допущения!$C$6*(1+Допущения!$C$7)^(F$27/12) -> 1062658.6 | G28: =Допущения!$C$6*(1+Допущения!$C$7)^(G$27/12) -> 1078927.3 | H28: =Допущения!$C$6*(1+Допущения!$C$7)^(H$27/12) -> 1095445.1 | I28: =Допущения!$C$6*(1+Допущения!$C$7)^(I$27/12) -> 1112215.8 | J28: =Допущения!$C$6*(1+Допущения!$C$7)^(J$27/12) -> 1129243.2 | ... AL28: =Допущения!$C$6*(1+Допущения!$C$7)^(AL$27/12) -> 1728000
A29: Активных пользователей помощника | C29: =IF(C$27<Допущения!$C$9,0,IF(C$27<Допущения!$C$10,Допущения!$C$8*Допущения!$C$13,C28*Допущения!$C$13*MIN(1,(C$27-Допущения!$C$10+1)/Допущения!$C$11))) -> 0 | D29: =IF(D$27<Допущения!$C$9,0,IF(D$27<Допущения!$C$10,Допущения!$C$8*Допущения!$C$13,D28*Допущения!$C$13*MIN(1,(D$27-Допущения!$C$10+1)/Допущения!$C$11))) -> 0 | E29: =IF(E$27<Допущения!$C$9,0,IF(E$27<Допущения!$C$10,Допущения!$C$8*Допущения!$C$13,E28*Допущения!$C$13*MIN(1,(E$27-Допущения!$C$10+1)/Допущения!$C$11))) -> 0 | F29: =IF(F$27<Допущения!$C$9,0,IF(F$27<Допущения!$C$10,Допущения!$C$8*Допущения!$C$13,F28*Допущения!$C$13*MIN(1,(F$27-Допущения!$C$10+1)/Допущения!$C$11))) -> 4000 | G29: =IF(G$27<Допущения!$C$9,0,IF(G$27<Допущения!$C$10,Допущения!$C$8*Допущения!$C$13,G28*Допущения!$C$13*MIN(1,(G$27-Допущения!$C$10+1)/Допущения!$C$11))) -> 4000 | H29: =IF(H$27<Допущения!$C$9,0,IF(H$27<Допущения!$C$10,Допущения!$C$8*Допущения!$C$13,H28*Допущения!$C$13*MIN(1,(H$27-Допущения!$C$10+1)/Допущения!$C$11))) -> 4000 | I29: =IF(I$27<Допущения!$C$9,0,IF(I$27<Допущения!$C$10,Допущения!$C$8*Допущения!$C$13,I28*Допущения!$C$13*MIN(1,(I$27-Допущения!$C$10+1)/Допущения!$C$11))) -> 18536.93 | J29: =IF(J$27<Допущения!$C$9,0,IF(J$27<Допущения!$C$10,Допущения!$C$8*Допущения!$C$13,J28*Допущения!$C$13*MIN(1,(J$27-Допущения!$C$10+1)/Допущения!$C$11))) -> 37641.441 | ... AL29: =IF(AL$27<Допущения!$C$9,0,IF(AL$27<Допущения!$C$10,Допущения!$C$8*Допущения!$C$13,AL28*Допущения!$C$13*MIN(1,(AL$27-Допущения!$C$10+1)/Допущения!$C$11))) -> 345600
A30: Новых ИП (прирост за счёт помощника) | C30: =C29*Допущения!$C$14/12*Допущения!$C$15 -> 0 | D30: =D29*Допущения!$C$14/12*Допущения!$C$15 -> 0 | E30: =E29*Допущения!$C$14/12*Допущения!$C$15 -> 0 | F30: =F29*Допущения!$C$14/12*Допущения!$C$15 -> 3.3333333 | G30: =G29*Допущения!$C$14/12*Допущения!$C$15 -> 3.3333333 | H30: =H29*Допущения!$C$14/12*Допущения!$C$15 -> 3.3333333 | I30: =I29*Допущения!$C$14/12*Допущения!$C$15 -> 15.447442 | J30: =J29*Допущения!$C$14/12*Допущения!$C$15 -> 31.367868 | ... AL30: =AL29*Допущения!$C$14/12*Допущения!$C$15 -> 288
A31: ИП на обслуживании | C31: =0*(1-Допущения!$C$19/12)+C30 -> 0 | D31: =C31*(1-Допущения!$C$19/12)+D30 -> 0 | E31: =D31*(1-Допущения!$C$19/12)+E30 -> 0 | F31: =E31*(1-Допущения!$C$19/12)+F30 -> 3.3333333 | G31: =F31*(1-Допущения!$C$19/12)+G30 -> 6.6111111 | H31: =G31*(1-Допущения!$C$19/12)+H30 -> 9.8342593 | I31: =H31*(1-Допущения!$C$19/12)+I30 -> 25.117797 | J31: =I31*(1-Допущения!$C$19/12)+J30 -> 56.067034 | K31: =J31*(1-Допущения!$C$19/12)+K30 -> 102.90472 | ... AL31: =AK31*(1-Допущения!$C$19/12)+AL30 -> 4949.8751
A32: Доход от ИП | C32: =C31*Допущения!$C$16/12 -> 0 | D32: =D31*Допущения!$C$16/12 -> 0 | E32: =E31*Допущения!$C$16/12 -> 0 | F32: =F31*Допущения!$C$16/12 -> 6944.4444 | G32: =G31*Допущения!$C$16/12 -> 13773.148 | H32: =H31*Допущения!$C$16/12 -> 20488.04 | I32: =I31*Допущения!$C$16/12 -> 52328.743 | J32: =J31*Допущения!$C$16/12 -> 116806.32 | ... AL32: =AL31*Допущения!$C$16/12 -> 10312240
A33: Экономия поддержки | C33: =C29*Допущения!$C$20/1000*Допущения!$C$21*Допущения!$C$22 -> 0 | D33: =D29*Допущения!$C$20/1000*Допущения!$C$21*Допущения!$C$22 -> 0 | E33: =E29*Допущения!$C$20/1000*Допущения!$C$21*Допущения!$C$22 -> 0 | F33: =F29*Допущения!$C$20/1000*Допущения!$C$21*Допущения!$C$22 -> 4800 | G33: =G29*Допущения!$C$20/1000*Допущения!$C$21*Допущения!$C$22 -> 4800 | H33: =H29*Допущения!$C$20/1000*Допущения!$C$21*Допущения!$C$22 -> 4800 | I33: =I29*Допущения!$C$20/1000*Допущения!$C$21*Допущения!$C$22 -> 22244.316 | J33: =J29*Допущения!$C$20/1000*Допущения!$C$21*Допущения!$C$22 -> 45169.729 | ... AL33: =AL29*Допущения!$C$20/1000*Допущения!$C$21*Допущения!$C$22 -> 414720
A34: Удержание клиентов | C34: =C29*Допущения!$C$17*Допущения!$C$23/12 -> 0 | D34: =D29*Допущения!$C$17*Допущения!$C$23/12 -> 0 | E34: =E29*Допущения!$C$17*Допущения!$C$23/12 -> 0 | F34: =F29*Допущения!$C$17*Допущения!$C$23/12 -> 10000 | G34: =G29*Допущения!$C$17*Допущения!$C$23/12 -> 10000 | H34: =H29*Допущения!$C$17*Допущения!$C$23/12 -> 10000 | I34: =I29*Допущения!$C$17*Допущения!$C$23/12 -> 46342.325 | J34: =J29*Допущения!$C$17*Допущения!$C$23/12 -> 94103.603 | ... AL34: =AL29*Допущения!$C$17*Допущения!$C$23/12 -> 864000
A35: Эффект всего | C35: =SUM(C32:C34) -> 0 | D35: =SUM(D32:D34) -> 0 | E35: =SUM(E32:E34) -> 0 | F35: =SUM(F32:F34) -> 21744.444 | G35: =SUM(G32:G34) -> 28573.148 | H35: =SUM(H32:H34) -> 35288.04 | I35: =SUM(I32:I34) -> 120915.38 | J35: =SUM(J32:J34) -> 256079.65 | ... AL35: =SUM(AL32:AL34) -> 11590960
A36: Серверов | C36: =MAX(Допущения!$C$35,ROUNDUP(C29/Допущения!$C$34,0)+1) -> 2 | D36: =MAX(Допущения!$C$35,ROUNDUP(D29/Допущения!$C$34,0)+1) -> 2 | E36: =MAX(Допущения!$C$35,ROUNDUP(E29/Допущения!$C$34,0)+1) -> 2 | F36: =MAX(Допущения!$C$35,ROUNDUP(F29/Допущения!$C$34,0)+1) -> 2 | G36: =MAX(Допущения!$C$35,ROUNDUP(G29/Допущения!$C$34,0)+1) -> 2 | H36: =MAX(Допущения!$C$35,ROUNDUP(H29/Допущения!$C$34,0)+1) -> 2 | I36: =MAX(Допущения!$C$35,ROUNDUP(I29/Допущения!$C$34,0)+1) -> 2 | J36: =MAX(Допущения!$C$35,ROUNDUP(J29/Допущения!$C$34,0)+1) -> 2 | ... AL36: =MAX(Допущения!$C$35,ROUNDUP(AL29/Допущения!$C$34,0)+1) -> 4
A37: Закупка серверов | C37: =(C36-0)*Допущения!$C$32 -> 8000000 | D37: =(D36-C36)*Допущения!$C$32 -> 0 | E37: =(E36-D36)*Допущения!$C$32 -> 0 | F37: =(F36-E36)*Допущения!$C$32 -> 0 | G37: =(G36-F36)*Допущения!$C$32 -> 0 | H37: =(H36-G36)*Допущения!$C$32 -> 0 | I37: =(I36-H36)*Допущения!$C$32 -> 0 | J37: =(J36-I36)*Допущения!$C$32 -> 0 | K37: =(K36-J36)*Допущения!$C$32 -> 0 | ... AL37: =(AL36-AK36)*Допущения!$C$32 -> 0
A38: Команда | C38: =IF(C$27<Допущения!$C$10,Допущения!$C$26,Допущения!$C$27)*Допущения!$C$25 -> 2400000 | D38: =IF(D$27<Допущения!$C$10,Допущения!$C$26,Допущения!$C$27)*Допущения!$C$25 -> 2400000 | E38: =IF(E$27<Допущения!$C$10,Допущения!$C$26,Допущения!$C$27)*Допущения!$C$25 -> 2400000 | F38: =IF(F$27<Допущения!$C$10,Допущения!$C$26,Допущения!$C$27)*Допущения!$C$25 -> 2400000 | G38: =IF(G$27<Допущения!$C$10,Допущения!$C$26,Допущения!$C$27)*Допущения!$C$25 -> 2400000 | H38: =IF(H$27<Допущения!$C$10,Допущения!$C$26,Допущения!$C$27)*Допущения!$C$25 -> 2400000 | I38: =IF(I$27<Допущения!$C$10,Допущения!$C$26,Допущения!$C$27)*Допущения!$C$25 -> 1200000 | J38: =IF(J$27<Допущения!$C$10,Допущения!$C$26,Допущения!$C$27)*Допущения!$C$25 -> 1200000 | ... AL38: =IF(AL$27<Допущения!$C$10,Допущения!$C$26,Допущения!$C$27)*Допущения!$C$25 -> 1200000
A39: Юрист | C39: =Допущения!$C$28*Допущения!$C$29 -> 150000 | D39: =Допущения!$C$28*Допущения!$C$29 -> 150000 | E39: =Допущения!$C$28*Допущения!$C$29 -> 150000 | F39: =Допущения!$C$28*Допущения!$C$29 -> 150000 | G39: =Допущения!$C$28*Допущения!$C$29 -> 150000 | H39: =Допущения!$C$28*Допущения!$C$29 -> 150000 | I39: =Допущения!$C$28*Допущения!$C$29 -> 150000 | J39: =Допущения!$C$28*Допущения!$C$29 -> 150000 | ... AL39: =Допущения!$C$28*Допущения!$C$29 -> 150000
A40: Информационная безопасность | C40: =Допущения!$C$30/12 -> 125000 | D40: =Допущения!$C$30/12 -> 125000 | E40: =Допущения!$C$30/12 -> 125000 | F40: =Допущения!$C$30/12 -> 125000 | G40: =Допущения!$C$30/12 -> 125000 | H40: =Допущения!$C$30/12 -> 125000 | I40: =Допущения!$C$30/12 -> 125000 | J40: =Допущения!$C$30/12 -> 125000 | ... AL40: =Допущения!$C$30/12 -> 125000
A41: Продвижение | C41: =IF(C$27>=Допущения!$C$10,Допущения!$C$31/12,0) -> 0 | D41: =IF(D$27>=Допущения!$C$10,Допущения!$C$31/12,0) -> 0 | E41: =IF(E$27>=Допущения!$C$10,Допущения!$C$31/12,0) -> 0 | F41: =IF(F$27>=Допущения!$C$10,Допущения!$C$31/12,0) -> 0 | G41: =IF(G$27>=Допущения!$C$10,Допущения!$C$31/12,0) -> 0 | H41: =IF(H$27>=Допущения!$C$10,Допущения!$C$31/12,0) -> 0 | I41: =IF(I$27>=Допущения!$C$10,Допущения!$C$31/12,0) -> 83333.333 | J41: =IF(J$27>=Допущения!$C$10,Допущения!$C$31/12,0) -> 83333.333 | ... AL41: =IF(AL$27>=Допущения!$C$10,Допущения!$C$31/12,0) -> 83333.333
A42: Эксплуатация серверов | C42: =C36*Допущения!$C$32*Допущения!$C$33/12 -> 100000 | D42: =D36*Допущения!$C$32*Допущения!$C$33/12 -> 100000 | E42: =E36*Допущения!$C$32*Допущения!$C$33/12 -> 100000 | F42: =F36*Допущения!$C$32*Допущения!$C$33/12 -> 100000 | G42: =G36*Допущения!$C$32*Допущения!$C$33/12 -> 100000 | H42: =H36*Допущения!$C$32*Допущения!$C$33/12 -> 100000 | I42: =I36*Допущения!$C$32*Допущения!$C$33/12 -> 100000 | J42: =J36*Допущения!$C$32*Допущения!$C$33/12 -> 100000 | ... AL42: =AL36*Допущения!$C$32*Допущения!$C$33/12 -> 200000
A43: Затраты всего | C43: =SUM(C37:C42) -> 10775000 | D43: =SUM(D37:D42) -> 2775000 | E43: =SUM(E37:E42) -> 2775000 | F43: =SUM(F37:F42) -> 2775000 | G43: =SUM(G37:G42) -> 2775000 | H43: =SUM(H37:H42) -> 2775000 | I43: =SUM(I37:I42) -> 1658333.3 | J43: =SUM(J37:J42) -> 1658333.3 | ... AL43: =SUM(AL37:AL42) -> 1758333.3
A44: Денежный поток | C44: =C35-C43 -> -10775000 | D44: =D35-D43 -> -2775000 | E44: =E35-E43 -> -2775000 | F44: =F35-F43 -> -2753255.6 | G44: =G35-G43 -> -2746426.9 | H44: =H35-H43 -> -2739712 | I44: =I35-I43 -> -1537417.9 | J44: =J35-J43 -> -1402253.7 | ... AL44: =AL35-AL43 -> 9832626.5
A45: Накопленный денежный поток | C45: =0+C44 -> -10775000 | D45: =C45+D44 -> -13550000 | E45: =D45+E44 -> -16325000 | F45: =E45+F44 -> -19078256 | G45: =F45+G44 -> -21824682 | H45: =G45+H44 -> -24564394 | I45: =H45+I44 -> -26101812 | J45: =I45+J44 -> -27504066 | K45: =J45+K44 -> -28735906 | ... AL45: =AK45+AL44 -> 74892574
A46: Месяц окупаемости (отметка) | C46: =IF(C45>=0,C$27,"") | D46: =IF(AND(D45>=0,C45<0),D$27,"") | E46: =IF(AND(E45>=0,D45<0),E$27,"") | F46: =IF(AND(F45>=0,E45<0),F$27,"") | G46: =IF(AND(G45>=0,F45<0),G$27,"") | H46: =IF(AND(H45>=0,G45<0),H$27,"") | I46: =IF(AND(I45>=0,H45<0),I$27,"") | J46: =IF(AND(J45>=0,I45<0),J$27,"") | K46: =IF(AND(K45>=0,J45<0),K$27,"") | ... AL46: =IF(AND(AL45>=0,AK45<0),AL$27,"")
A49: Сценарий: Оптимистичный
A50: Месяц | C50: 1 | D50: 2 | E50: 3 | F50: 4 | G50: 5 | H50: 6 | I50: 7 | J50: 8 | K50: 9 | L50: 10 | M50: 11 | N50: 12 | O50: 13 | P50: 14 | Q50: 15 | R50: 16 | S50: 17 | T50: 18 | U50: 19 | V50: 20 | W50: 21 | X50: 22 | Y50: 23 | Z50: 24 | AA50: 25 | AB50: 26 | AC50: 27 | AD50: 28 | AE50: 29 | AF50: 30 | AG50: 31 | AH50: 32 | AI50: 33 | AJ50: 34 | AK50: 35 | AL50: 36
A51: База самозанятых клиентов | C51: =Допущения!$C$6*(1+Допущения!$C$7)^(C$50/12) -> 1015309.5 | D51: =Допущения!$C$6*(1+Допущения!$C$7)^(D$50/12) -> 1030853.3 | E51: =Допущения!$C$6*(1+Допущения!$C$7)^(E$50/12) -> 1046635.1 | F51: =Допущения!$C$6*(1+Допущения!$C$7)^(F$50/12) -> 1062658.6 | G51: =Допущения!$C$6*(1+Допущения!$C$7)^(G$50/12) -> 1078927.3 | H51: =Допущения!$C$6*(1+Допущения!$C$7)^(H$50/12) -> 1095445.1 | I51: =Допущения!$C$6*(1+Допущения!$C$7)^(I$50/12) -> 1112215.8 | J51: =Допущения!$C$6*(1+Допущения!$C$7)^(J$50/12) -> 1129243.2 | ... AL51: =Допущения!$C$6*(1+Допущения!$C$7)^(AL$50/12) -> 1728000
A52: Активных пользователей помощника | C52: =IF(C$50<Допущения!$C$9,0,IF(C$50<Допущения!$C$10,Допущения!$C$8*Допущения!$D$13,C51*Допущения!$D$13*MIN(1,(C$50-Допущения!$C$10+1)/Допущения!$C$11))) -> 0 | D52: =IF(D$50<Допущения!$C$9,0,IF(D$50<Допущения!$C$10,Допущения!$C$8*Допущения!$D$13,D51*Допущения!$D$13*MIN(1,(D$50-Допущения!$C$10+1)/Допущения!$C$11))) -> 0 | E52: =IF(E$50<Допущения!$C$9,0,IF(E$50<Допущения!$C$10,Допущения!$C$8*Допущения!$D$13,E51*Допущения!$D$13*MIN(1,(E$50-Допущения!$C$10+1)/Допущения!$C$11))) -> 0 | F52: =IF(F$50<Допущения!$C$9,0,IF(F$50<Допущения!$C$10,Допущения!$C$8*Допущения!$D$13,F51*Допущения!$D$13*MIN(1,(F$50-Допущения!$C$10+1)/Допущения!$C$11))) -> 6000 | G52: =IF(G$50<Допущения!$C$9,0,IF(G$50<Допущения!$C$10,Допущения!$C$8*Допущения!$D$13,G51*Допущения!$D$13*MIN(1,(G$50-Допущения!$C$10+1)/Допущения!$C$11))) -> 6000 | H52: =IF(H$50<Допущения!$C$9,0,IF(H$50<Допущения!$C$10,Допущения!$C$8*Допущения!$D$13,H51*Допущения!$D$13*MIN(1,(H$50-Допущения!$C$10+1)/Допущения!$C$11))) -> 6000 | I52: =IF(I$50<Допущения!$C$9,0,IF(I$50<Допущения!$C$10,Допущения!$C$8*Допущения!$D$13,I51*Допущения!$D$13*MIN(1,(I$50-Допущения!$C$10+1)/Допущения!$C$11))) -> 27805.395 | J52: =IF(J$50<Допущения!$C$9,0,IF(J$50<Допущения!$C$10,Допущения!$C$8*Допущения!$D$13,J51*Допущения!$D$13*MIN(1,(J$50-Допущения!$C$10+1)/Допущения!$C$11))) -> 56462.162 | ... AL52: =IF(AL$50<Допущения!$C$9,0,IF(AL$50<Допущения!$C$10,Допущения!$C$8*Допущения!$D$13,AL51*Допущения!$D$13*MIN(1,(AL$50-Допущения!$C$10+1)/Допущения!$C$11))) -> 518400
A53: Новых ИП (прирост за счёт помощника) | C53: =C52*Допущения!$D$14/12*Допущения!$D$15 -> 0 | D53: =D52*Допущения!$D$14/12*Допущения!$D$15 -> 0 | E53: =E52*Допущения!$D$14/12*Допущения!$D$15 -> 0 | F53: =F52*Допущения!$D$14/12*Допущения!$D$15 -> 9 | G53: =G52*Допущения!$D$14/12*Допущения!$D$15 -> 9 | H53: =H52*Допущения!$D$14/12*Допущения!$D$15 -> 9 | I53: =I52*Допущения!$D$14/12*Допущения!$D$15 -> 41.708092 | J53: =J52*Допущения!$D$14/12*Допущения!$D$15 -> 84.693243 | ... AL53: =AL52*Допущения!$D$14/12*Допущения!$D$15 -> 777.6
A54: ИП на обслуживании | C54: =0*(1-Допущения!$C$19/12)+C53 -> 0 | D54: =C54*(1-Допущения!$C$19/12)+D53 -> 0 | E54: =D54*(1-Допущения!$C$19/12)+E53 -> 0 | F54: =E54*(1-Допущения!$C$19/12)+F53 -> 9 | G54: =F54*(1-Допущения!$C$19/12)+G53 -> 17.85 | H54: =G54*(1-Допущения!$C$19/12)+H53 -> 26.5525 | I54: =H54*(1-Допущения!$C$19/12)+I53 -> 67.818051 | J54: =I54*(1-Допущения!$C$19/12)+J53 -> 151.38099 | K54: =J54*(1-Допущения!$C$19/12)+K53 -> 277.84275 | ... AL54: =AK54*(1-Допущения!$C$19/12)+AL53 -> 13364.663
A55: Доход от ИП | C55: =C54*Допущения!$D$16/12 -> 0 | D55: =D54*Допущения!$D$16/12 -> 0 | E55: =E54*Допущения!$D$16/12 -> 0 | F55: =F54*Допущения!$D$16/12 -> 26250 | G55: =G54*Допущения!$D$16/12 -> 52062.5 | H55: =H54*Допущения!$D$16/12 -> 77444.792 | I55: =I54*Допущения!$D$16/12 -> 197802.65 | J55: =J54*Допущения!$D$16/12 -> 441527.9 | ... AL55: =AL54*Допущения!$D$16/12 -> 38980267
A56: Экономия поддержки | C56: =C52*Допущения!$C$20/1000*Допущения!$C$21*Допущения!$C$22 -> 0 | D56: =D52*Допущения!$C$20/1000*Допущения!$C$21*Допущения!$C$22 -> 0 | E56: =E52*Допущения!$C$20/1000*Допущения!$C$21*Допущения!$C$22 -> 0 | F56: =F52*Допущения!$C$20/1000*Допущения!$C$21*Допущения!$C$22 -> 7200 | G56: =G52*Допущения!$C$20/1000*Допущения!$C$21*Допущения!$C$22 -> 7200 | H56: =H52*Допущения!$C$20/1000*Допущения!$C$21*Допущения!$C$22 -> 7200 | I56: =I52*Допущения!$C$20/1000*Допущения!$C$21*Допущения!$C$22 -> 33366.474 | J56: =J52*Допущения!$C$20/1000*Допущения!$C$21*Допущения!$C$22 -> 67754.594 | ... AL56: =AL52*Допущения!$C$20/1000*Допущения!$C$21*Допущения!$C$22 -> 622080
A57: Удержание клиентов | C57: =C52*Допущения!$D$17*Допущения!$C$23/12 -> 0 | D57: =D52*Допущения!$D$17*Допущения!$C$23/12 -> 0 | E57: =E52*Допущения!$D$17*Допущения!$C$23/12 -> 0 | F57: =F52*Допущения!$D$17*Допущения!$C$23/12 -> 30000 | G57: =G52*Допущения!$D$17*Допущения!$C$23/12 -> 30000 | H57: =H52*Допущения!$D$17*Допущения!$C$23/12 -> 30000 | I57: =I52*Допущения!$D$17*Допущения!$C$23/12 -> 139026.97 | J57: =J52*Допущения!$D$17*Допущения!$C$23/12 -> 282310.81 | ... AL57: =AL52*Допущения!$D$17*Допущения!$C$23/12 -> 2592000
A58: Эффект всего | C58: =SUM(C55:C57) -> 0 | D58: =SUM(D55:D57) -> 0 | E58: =SUM(E55:E57) -> 0 | F58: =SUM(F55:F57) -> 63450 | G58: =SUM(G55:G57) -> 89262.5 | H58: =SUM(H55:H57) -> 114644.79 | I58: =SUM(I55:I57) -> 370196.1 | J58: =SUM(J55:J57) -> 791593.3 | ... AL58: =SUM(AL55:AL57) -> 42194347
A59: Серверов | C59: =MAX(Допущения!$C$35,ROUNDUP(C52/Допущения!$C$34,0)+1) -> 2 | D59: =MAX(Допущения!$C$35,ROUNDUP(D52/Допущения!$C$34,0)+1) -> 2 | E59: =MAX(Допущения!$C$35,ROUNDUP(E52/Допущения!$C$34,0)+1) -> 2 | F59: =MAX(Допущения!$C$35,ROUNDUP(F52/Допущения!$C$34,0)+1) -> 2 | G59: =MAX(Допущения!$C$35,ROUNDUP(G52/Допущения!$C$34,0)+1) -> 2 | H59: =MAX(Допущения!$C$35,ROUNDUP(H52/Допущения!$C$34,0)+1) -> 2 | I59: =MAX(Допущения!$C$35,ROUNDUP(I52/Допущения!$C$34,0)+1) -> 2 | J59: =MAX(Допущения!$C$35,ROUNDUP(J52/Допущения!$C$34,0)+1) -> 2 | ... AL59: =MAX(Допущения!$C$35,ROUNDUP(AL52/Допущения!$C$34,0)+1) -> 5
A60: Закупка серверов | C60: =(C59-0)*Допущения!$C$32 -> 8000000 | D60: =(D59-C59)*Допущения!$C$32 -> 0 | E60: =(E59-D59)*Допущения!$C$32 -> 0 | F60: =(F59-E59)*Допущения!$C$32 -> 0 | G60: =(G59-F59)*Допущения!$C$32 -> 0 | H60: =(H59-G59)*Допущения!$C$32 -> 0 | I60: =(I59-H59)*Допущения!$C$32 -> 0 | J60: =(J59-I59)*Допущения!$C$32 -> 0 | K60: =(K59-J59)*Допущения!$C$32 -> 0 | ... AL60: =(AL59-AK59)*Допущения!$C$32 -> 0
A61: Команда | C61: =IF(C$50<Допущения!$C$10,Допущения!$C$26,Допущения!$C$27)*Допущения!$C$25 -> 2400000 | D61: =IF(D$50<Допущения!$C$10,Допущения!$C$26,Допущения!$C$27)*Допущения!$C$25 -> 2400000 | E61: =IF(E$50<Допущения!$C$10,Допущения!$C$26,Допущения!$C$27)*Допущения!$C$25 -> 2400000 | F61: =IF(F$50<Допущения!$C$10,Допущения!$C$26,Допущения!$C$27)*Допущения!$C$25 -> 2400000 | G61: =IF(G$50<Допущения!$C$10,Допущения!$C$26,Допущения!$C$27)*Допущения!$C$25 -> 2400000 | H61: =IF(H$50<Допущения!$C$10,Допущения!$C$26,Допущения!$C$27)*Допущения!$C$25 -> 2400000 | I61: =IF(I$50<Допущения!$C$10,Допущения!$C$26,Допущения!$C$27)*Допущения!$C$25 -> 1200000 | J61: =IF(J$50<Допущения!$C$10,Допущения!$C$26,Допущения!$C$27)*Допущения!$C$25 -> 1200000 | ... AL61: =IF(AL$50<Допущения!$C$10,Допущения!$C$26,Допущения!$C$27)*Допущения!$C$25 -> 1200000
A62: Юрист | C62: =Допущения!$C$28*Допущения!$C$29 -> 150000 | D62: =Допущения!$C$28*Допущения!$C$29 -> 150000 | E62: =Допущения!$C$28*Допущения!$C$29 -> 150000 | F62: =Допущения!$C$28*Допущения!$C$29 -> 150000 | G62: =Допущения!$C$28*Допущения!$C$29 -> 150000 | H62: =Допущения!$C$28*Допущения!$C$29 -> 150000 | I62: =Допущения!$C$28*Допущения!$C$29 -> 150000 | J62: =Допущения!$C$28*Допущения!$C$29 -> 150000 | ... AL62: =Допущения!$C$28*Допущения!$C$29 -> 150000
A63: Информационная безопасность | C63: =Допущения!$C$30/12 -> 125000 | D63: =Допущения!$C$30/12 -> 125000 | E63: =Допущения!$C$30/12 -> 125000 | F63: =Допущения!$C$30/12 -> 125000 | G63: =Допущения!$C$30/12 -> 125000 | H63: =Допущения!$C$30/12 -> 125000 | I63: =Допущения!$C$30/12 -> 125000 | J63: =Допущения!$C$30/12 -> 125000 | ... AL63: =Допущения!$C$30/12 -> 125000
A64: Продвижение | C64: =IF(C$50>=Допущения!$C$10,Допущения!$C$31/12,0) -> 0 | D64: =IF(D$50>=Допущения!$C$10,Допущения!$C$31/12,0) -> 0 | E64: =IF(E$50>=Допущения!$C$10,Допущения!$C$31/12,0) -> 0 | F64: =IF(F$50>=Допущения!$C$10,Допущения!$C$31/12,0) -> 0 | G64: =IF(G$50>=Допущения!$C$10,Допущения!$C$31/12,0) -> 0 | H64: =IF(H$50>=Допущения!$C$10,Допущения!$C$31/12,0) -> 0 | I64: =IF(I$50>=Допущения!$C$10,Допущения!$C$31/12,0) -> 83333.333 | J64: =IF(J$50>=Допущения!$C$10,Допущения!$C$31/12,0) -> 83333.333 | ... AL64: =IF(AL$50>=Допущения!$C$10,Допущения!$C$31/12,0) -> 83333.333
A65: Эксплуатация серверов | C65: =C59*Допущения!$C$32*Допущения!$C$33/12 -> 100000 | D65: =D59*Допущения!$C$32*Допущения!$C$33/12 -> 100000 | E65: =E59*Допущения!$C$32*Допущения!$C$33/12 -> 100000 | F65: =F59*Допущения!$C$32*Допущения!$C$33/12 -> 100000 | G65: =G59*Допущения!$C$32*Допущения!$C$33/12 -> 100000 | H65: =H59*Допущения!$C$32*Допущения!$C$33/12 -> 100000 | I65: =I59*Допущения!$C$32*Допущения!$C$33/12 -> 100000 | J65: =J59*Допущения!$C$32*Допущения!$C$33/12 -> 100000 | ... AL65: =AL59*Допущения!$C$32*Допущения!$C$33/12 -> 250000
A66: Затраты всего | C66: =SUM(C60:C65) -> 10775000 | D66: =SUM(D60:D65) -> 2775000 | E66: =SUM(E60:E65) -> 2775000 | F66: =SUM(F60:F65) -> 2775000 | G66: =SUM(G60:G65) -> 2775000 | H66: =SUM(H60:H65) -> 2775000 | I66: =SUM(I60:I65) -> 1658333.3 | J66: =SUM(J60:J65) -> 1658333.3 | ... AL66: =SUM(AL60:AL65) -> 1808333.3
A67: Денежный поток | C67: =C58-C66 -> -10775000 | D67: =D58-D66 -> -2775000 | E67: =E58-E66 -> -2775000 | F67: =F58-F66 -> -2711550 | G67: =G58-G66 -> -2685737.5 | H67: =H58-H66 -> -2660355.2 | I67: =I58-I66 -> -1288137.2 | J67: =J58-J66 -> -866740.04 | ... AL67: =AL58-AL66 -> 40386013
A68: Накопленный денежный поток | C68: =0+C67 -> -10775000 | D68: =C68+D67 -> -13550000 | E68: =D68+E67 -> -16325000 | F68: =E68+F67 -> -19036550 | G68: =F68+G67 -> -21722288 | H68: =G68+H67 -> -24382643 | I68: =H68+I67 -> -25670780 | J68: =I68+J67 -> -26537520 | K68: =J68+K67 -> -26852342 | ... AL68: =AK68+AL67 -> 4.7826667e+08
A69: Месяц окупаемости (отметка) | C69: =IF(C68>=0,C$50,"") | D69: =IF(AND(D68>=0,C68<0),D$50,"") | E69: =IF(AND(E68>=0,D68<0),E$50,"") | F69: =IF(AND(F68>=0,E68<0),F$50,"") | G69: =IF(AND(G68>=0,F68<0),G$50,"") | H69: =IF(AND(H68>=0,G68<0),H$50,"") | I69: =IF(AND(I68>=0,H68<0),I$50,"") | J69: =IF(AND(J68>=0,I68<0),J$50,"") | K69: =IF(AND(K68>=0,J68<0),K$50,"") | ... AL69: =IF(AND(AL68>=0,AK68<0),AL$50,"")

Sheet Источники
A1: Источники
A3: 1 | B3: ВТБ: по итогам 2025 года число клиентов-самозанятых выросло на 43% и превысило 1 млн; клиенты МСБ ВТБ сделали более 170 тыс. переводов самозанятым на 12,4 млрд ₽ — Д. Бортников, «Газета.Ru», 18.02.2026 | C3: https://finance.mail.ru/article/samozanyatyie-rossiyane-stali-rekordno-vostrebovannyimi-69198919/
A4: 2 | B4: ФНС (ТАСС): 17,3 млн самозанятых, за год +2,9 млн; выручка самозанятых за июль 2026 — 299,3 млрд ₽, начислено налогов — 13,4 млрд ₽ — 21.08.2026 | C4: https://fomag.ru/news-streem/obshchee-kolichestvo-samozanyatykh-v-rossii-prevysilo-17-mln-chelovek-fns/
A5: 3 | B5: Платформа данных ФНС: 17,263 млн самозанятых; 15,43 млн на конец 2025 года; в июле 2026 — 476,5 тыс. регистраций и 227,49 млн чеков — Sostav, 21.08.2026 | C5: https://www.sostav.ru/publication/chislo-samozanyatykh-v-rossii-prevysilo-17-2-mln-86292.html
A6: 4 | B6: ФНС: 53% самозанятых моложе 35 лет, 23% — моложе 26 лет; средний возраст 36 лет — nalog.gov.ru, 06.02.2025 | C6: https://www.nalog.gov.ru/rn77/news/activities_fts/15703488/
A7: 5 | B7: ВТБ: портрет самозанятых клиентов — поколение Z 16%, Y 48%, X 29% — Т—Ж, 18.06.2025 | C7: https://t-j.ru/news/vtb-selfemployed-portrait/
A8: 6 | B8: Качество помощника: эталонные прогоны прототипа | C8: https://github.com/imaO0O/vtb/tree/main/eval/results
